rsHRF/CLI.py
rsHRF/VERSION
rsHRF/__about__.py
rsHRF/__init__.py
rsHRF/__main__.py
rsHRF/fourD_rsHRF.py
rsHRF/iterative_wiener_deconv.py
rsHRF/parameters.py
rsHRF/basis_functions/__init__.py
rsHRF/basis_functions/basis_functions.py
rsHRF/canon/__init__.py
rsHRF/canon/canon_hrf2dd.py
rsHRF/processing/__init__.py
rsHRF/processing/knee.py
rsHRF/processing/rest_filter.py
rsHRF/rsHRF_GUI/__init__.py
rsHRF/rsHRF_GUI/run.py
rsHRF/rsHRF_GUI/core/__init__.py
rsHRF/rsHRF_GUI/core/core.py
rsHRF/rsHRF_GUI/datatypes/__init__.py
rsHRF/rsHRF_GUI/datatypes/misc/__init__.py
rsHRF/rsHRF_GUI/datatypes/misc/parameters.py
rsHRF/rsHRF_GUI/datatypes/misc/store.py
rsHRF/rsHRF_GUI/datatypes/misc/subject.py
rsHRF/rsHRF_GUI/datatypes/timeseries/__init__.py
rsHRF/rsHRF_GUI/datatypes/timeseries/bold_deconv.py
rsHRF/rsHRF_GUI/datatypes/timeseries/bold_preprocessed.py
rsHRF/rsHRF_GUI/datatypes/timeseries/bold_raw.py
rsHRF/rsHRF_GUI/datatypes/timeseries/hrf.py
rsHRF/rsHRF_GUI/datatypes/timeseries/timeseries.py
rsHRF/rsHRF_GUI/gui_windows/__init__.py
rsHRF/rsHRF_GUI/gui_windows/inputWindow.py
rsHRF/rsHRF_GUI/gui_windows/loggingWindow.py
rsHRF/rsHRF_GUI/gui_windows/main.py
rsHRF/rsHRF_GUI/gui_windows/parameterWindow.py
rsHRF/rsHRF_GUI/gui_windows/plotterOptionsWindow.py
rsHRF/rsHRF_GUI/gui_windows/plotterWindow.py
rsHRF/rsHRF_GUI/misc/__init__.py
rsHRF/rsHRF_GUI/misc/status.py
rsHRF/sFIR/__init__.py
rsHRF/sFIR/smooth_fir.py
rsHRF/spm_dep/__init__.py
rsHRF/spm_dep/spm.py
rsHRF/unit_tests/__init__.py
rsHRF/unit_tests/test_basis_functions.py
rsHRF/unit_tests/test_canon_hrf2dd.py
rsHRF/unit_tests/test_iterative_wiener_deconv.py
rsHRF/unit_tests/test_knee.py
rsHRF/unit_tests/test_parameters.py
rsHRF/unit_tests/test_rest_filter.py
rsHRF/unit_tests/test_smooth_fir.py
rsHRF/unit_tests/test_spm.py
rsHRF/utils/__init__.py
rsHRF/utils/bids.py
rsHRF/utils/hrf_estimation.py
rsHRF-1.5.8.dist-info/LICENSE
rsHRF-1.5.8.dist-info/METADATA
rsHRF-1.5.8.dist-info/WHEEL
rsHRF-1.5.8.dist-info/entry_points.txt
rsHRF-1.5.8.dist-info/top_level.txt
rsHRF-1.5.8.dist-info/RECORD
