Metadata-Version: 2.1
Name: rsHRF
Version: 1.5.8
Summary: BIDs App to retrieve the haemodynamic response function from resting state fMRI data
Home-page: https://github.com/BIDS-Apps/rsHRF
Author: Madhur Tandon, Amogh Johri
Author-email: madhurtandon23@gmail.com, amogh.johri@iiitb.org
License: MIT
Platform: UNKNOWN
Classifier: Programming Language :: Python :: 3
Classifier: License :: OSI Approved :: MIT License
Classifier: Operating System :: OS Independent
Requires-Python: >=3.6
License-File: LICENSE
Requires-Dist: numpy
Requires-Dist: nibabel
Requires-Dist: matplotlib
Requires-Dist: scipy
Requires-Dist: pybids (==0.11.1)
Requires-Dist: pandas
Requires-Dist: patsy
Requires-Dist: mpld3
Requires-Dist: duecredit
Requires-Dist: joblib
Requires-Dist: pyyawt
